dagster_bash/__init__.py
dagster_bash/solids.py
dagster_bash/utils.py
dagster_bash/version.py
dagster_bash_tests/__init__.py
dagster_bash_tests/conftest.py
dagster_bash_tests/example_bash_command_solid.py
dagster_bash_tests/example_bash_script_solid.py
dagster_bash_tests/test_examples.py
dagster_bash_tests/test_solids.py
dagster_bash_tests/test_utils.py
dagster_bash_tests/test_version.py
dagster_bash-0.7.16.dist-info/LICENSE
dagster_bash-0.7.16.dist-info/METADATA
dagster_bash-0.7.16.dist-info/WHEEL
dagster_bash-0.7.16.dist-info/top_level.txt
dagster_bash-0.7.16.dist-info/RECORD
