Metadata-Version: 2.1
Name: dagster-bash
Version: 0.7.16
Summary: Package for Dagster bash solids.
Home-page: https://github.com/dagster-io/dagster/tree/master/python_modules/libraries/dagster-bash
Author: Elementl
Author-email: UNKNOWN
License: Apache-2.0
Platform: UNKNOWN
Classifier: Programming Language :: Python :: 2.7
Classifier: Programming Language :: Python :: 3.5
Classifier: Programming Language :: Python :: 3.6
Classifier: License :: OSI Approved :: Apache Software License
Classifier: Operating System :: OS Independent
Requires-Dist: dagster
